.gitignore
README.md
setup.py
definitive_screening_design/__init__.py
definitive_screening_design/_generalized_dsd.py
definitive_screening_design/analysis.py
definitive_screening_design/design.py
definitive_screening_design.egg-info/PKG-INFO
definitive_screening_design.egg-info/SOURCES.txt
definitive_screening_design.egg-info/dependency_links.txt
definitive_screening_design.egg-info/requires.txt
definitive_screening_design.egg-info/top_level.txt
notebooks/1_introduction_to_dsd.ipynb
notebooks/2_analysis_of_design.ipynb
notebooks/3_analysis_of_response.ipynb
tests/__init__.py
tests/test_A.py