Metadata-Version: 2.1
Name: definitive-screening-design
Version: 0.5.0
Summary: Definitive Screening Design
Home-page: https://github.com/danieleongari/definitive_screening_design
Author: Daniele Ongari
Author-email: Daniele.Ongari@Solvay.com
License: None
Platform: UNKNOWN
Classifier: Programming Language :: Python
Provides-Extra: dev
